MANIFEST.in
README.md
setup.cfg
setup.py
spacy_sentence_bert/__init__.py
spacy_sentence_bert/language.py
spacy_sentence_bert/util.py
spacy_sentence_bert.egg-info/PKG-INFO
spacy_sentence_bert.egg-info/SOURCES.txt
spacy_sentence_bert.egg-info/dependency_links.txt
spacy_sentence_bert.egg-info/entry_points.txt
spacy_sentence_bert.egg-info/requires.txt
spacy_sentence_bert.egg-info/top_level.txt
spacy_sentence_bert/meta/en_allenai_specter.json
spacy_sentence_bert/meta/en_average_word_embeddings_glove_6B_300d.json
spacy_sentence_bert/meta/en_average_word_embeddings_glove_840B_300d.json
spacy_sentence_bert/meta/en_average_word_embeddings_komninos.json
spacy_sentence_bert/meta/en_average_word_embeddings_levy_dependency.json
spacy_sentence_bert/meta/en_msmarco_distilbert_base_v2.json
spacy_sentence_bert/meta/en_msmarco_distilroberta_base_v2.json
spacy_sentence_bert/meta/en_msmarco_roberta_base_v2.json
spacy_sentence_bert/meta/en_nli_bert_base.json
spacy_sentence_bert/meta/en_nli_bert_base_cls_pooling.json
spacy_sentence_bert/meta/en_nli_bert_base_max_pooling.json
spacy_sentence_bert/meta/en_nli_bert_large.json
spacy_sentence_bert/meta/en_nli_bert_large_cls_pooling.json
spacy_sentence_bert/meta/en_nli_bert_large_max_pooling.json
spacy_sentence_bert/meta/en_nli_distilbert_base.json
spacy_sentence_bert/meta/en_nli_distilbert_base_max_pooling.json
spacy_sentence_bert/meta/en_nli_roberta_base.json
spacy_sentence_bert/meta/en_nli_roberta_large.json
spacy_sentence_bert/meta/en_nq_distilbert_base_v1.json
spacy_sentence_bert/meta/en_paraphrase_distilroberta_base_v1.json
spacy_sentence_bert/meta/en_quora_distilbert_base.json
spacy_sentence_bert/meta/en_stsb_bert_base.json
spacy_sentence_bert/meta/en_stsb_bert_large.json
spacy_sentence_bert/meta/en_stsb_distilbert_base.json
spacy_sentence_bert/meta/en_stsb_roberta_base.json
spacy_sentence_bert/meta/en_stsb_roberta_large.json
spacy_sentence_bert/meta/xx_LaBSE.json
spacy_sentence_bert/meta/xx_cross_en_de_roberta_sentence_transformer.json
spacy_sentence_bert/meta/xx_distiluse_base_multilingual_cased_v2.json
spacy_sentence_bert/meta/xx_paraphrase_xlm_r_multilingual_v1.json
spacy_sentence_bert/meta/xx_quora_distilbert_multilingual.json
spacy_sentence_bert/meta/xx_stsb_xlm_r_multilingual.json