Metadata-Version: 2.1
Name: spacy-sentence-bert
Version: 0.1.2
Summary: SpaCy models for using sentence-BERT
Home-page: https://github.com/MartinoMensio/spacy-sentence-bert
Author: Martino Mensio
Author-email: martino.mensio@open.ac.uk
License: UNKNOWN
Platform: UNKNOWN
